odoo/addons/pos_restaurant_multi_company/README.rst
odoo/addons/pos_restaurant_multi_company/__init__.py
odoo/addons/pos_restaurant_multi_company/__manifest__.py
odoo/addons/pos_restaurant_multi_company/hooks.py
odoo/addons/pos_restaurant_multi_company/i18n/fr.po
odoo/addons/pos_restaurant_multi_company/i18n/pos_restaurant_multi_company.pot
odoo/addons/pos_restaurant_multi_company/models/__init__.py
odoo/addons/pos_restaurant_multi_company/models/restaurant_floor.py
odoo/addons/pos_restaurant_multi_company/models/restaurant_printer.py
odoo/addons/pos_restaurant_multi_company/models/restaurant_table.py
odoo/addons/pos_restaurant_multi_company/readme/CONTRIBUTORS.rst
odoo/addons/pos_restaurant_multi_company/readme/DESCRIPTION.rst
odoo/addons/pos_restaurant_multi_company/security/ir_rule.xml
odoo/addons/pos_restaurant_multi_company/static/description/icon.png
odoo/addons/pos_restaurant_multi_company/static/description/index.html
odoo/addons/pos_restaurant_multi_company/views/restaurant_floor.xml
odoo/addons/pos_restaurant_multi_company/views/restaurant_printer.xml
odoo12_addon_pos_restaurant_multi_company-12.0.1.0.0.99.dev4.dist-info/METADATA
odoo12_addon_pos_restaurant_multi_company-12.0.1.0.0.99.dev4.dist-info/WHEEL
odoo12_addon_pos_restaurant_multi_company-12.0.1.0.0.99.dev4.dist-info/top_level.txt
odoo12_addon_pos_restaurant_multi_company-12.0.1.0.0.99.dev4.dist-info/RECORD
